eduai/__init__.py
eduai/cli/__init__.py
eduai/cli/__main__.py
eduai/cli/main.py
eduai/core/__init__.py
eduai/core/engine.py
eduai/models/__init__.py
eduai/models/fallback_model.py
eduai/models/gemini_model.py
eduai/models/openai_model.py
eduai-0.1.0.dist-info/licenses/LICENSE
eduai-0.1.0.dist-info/METADATA
eduai-0.1.0.dist-info/WHEEL
eduai-0.1.0.dist-info/top_level.txt
eduai-0.1.0.dist-info/RECORD
