Metadata-Version: 2.4
Name: eduai
Version: 0.1.0
Summary: AI-powered educational translation tool for students and teachers
Home-page: https://github.com/yourusername/eduai
Author: Ahmad
Author-email: ahmad,sudais.work@example.com
Classifier: Programming Language :: Python :: 3
Classifier: License :: OSI Approved :: MIT License
Classifier: Operating System :: OS Independent
Requires-Python: >=3.8
License-File: LICENSE
Requires-Dist: openai
Requires-Dist: googletrans==4.0.0rc1
Dynamic: author
Dynamic: author-email
Dynamic: classifier
Dynamic: description
Dynamic: description-content-type
Dynamic: home-page
Dynamic: license-file
Dynamic: requires-dist
Dynamic: requires-python
Dynamic: summary
